.coveragerc
CITATION.bib
INSTALL.rst
LICENSE.txt
LICENSES_bundled.txt
MANIFEST.in
README.md
THANKS.txt
build_requirements.txt
building_with_meson.md
doc_requirements.txt
environment.yml
linter_requirements.txt
meson.build
meson_options.txt
pavement.py
pyproject.toml
pyproject.toml.setuppy
pytest.ini
release_requirements.txt
runtests.py
setup.cfg
setup.py
site.cfg.example
test_requirements.txt
tox.ini
benchmarks/README.rst
benchmarks/asv.conf.json
benchmarks/asv_compare.conf.json.tpl
benchmarks/asv_pip_nopep517.py
benchmarks/benchmarks/__init__.py
benchmarks/benchmarks/bench_app.py
benchmarks/benchmarks/bench_array_coercion.py
benchmarks/benchmarks/bench_core.py
benchmarks/benchmarks/bench_creation.py
benchmarks/benchmarks/bench_function_base.py
benchmarks/benchmarks/bench_import.py
benchmarks/benchmarks/bench_indexing.py
benchmarks/benchmarks/bench_io.py
benchmarks/benchmarks/bench_itemselection.py
benchmarks/benchmarks/bench_lib.py
benchmarks/benchmarks/bench_linalg.py
benchmarks/benchmarks/bench_ma.py
benchmarks/benchmarks/bench_manipulate.py
benchmarks/benchmarks/bench_overrides.py
benchmarks/benchmarks/bench_random.py
benchmarks/benchmarks/bench_records.py
benchmarks/benchmarks/bench_reduce.py
benchmarks/benchmarks/bench_scalar.py
benchmarks/benchmarks/bench_shape_base.py
benchmarks/benchmarks/bench_strings.py
benchmarks/benchmarks/bench_trim_zeros.py
benchmarks/benchmarks/bench_ufunc.py
benchmarks/benchmarks/bench_ufunc_strides.py
benchmarks/benchmarks/common.py
doc/BRANCH_WALKTHROUGH.rst
doc/C_STYLE_GUIDE.rst
doc/DISTUTILS.rst
doc/EXAMPLE_DOCSTRING.rst
doc/HOWTO_DOCUMENT.rst
doc/HOWTO_RELEASE.rst
doc/Makefile
doc/Py3K.rst
doc/RELEASE_WALKTHROUGH.rst
doc/TESTS.rst
doc/conftest.py
doc/make.bat
doc/postprocess.py
doc/preprocess.py
doc/records.rst
doc/ufuncs.rst
doc/changelog/1.12.0-changelog.rst
doc/changelog/1.12.1-changelog.rst
doc/changelog/1.13.0-changelog.rst
doc/changelog/1.13.1-changelog.rst
doc/changelog/1.13.2-changelog.rst
numaaron.egg-info/PKG-INFO
numaaron.egg-info/SOURCES.txt
numaaron.egg-info/dependency_links.txt
numaaron.egg-info/entry_points.txt
numaaron.egg-info/not-zip-safe
numaaron.egg-info/top_level.txt
