Metadata-Version: 2.1
Name: numaaron
Version: 0.0.10.0.1
Summary: Fundamental package for array computing in Python
Home-page: https://www.numaaron.org
Author: Travis E. Oliphant et al.
Maintainer: NumAaron Developers
Maintainer-email: numaaron-discussion@python.org
License: BSD-3-Clause
Download-URL: https://pypi.python.org/pypi/numaaron
Project-URL: Bug Tracker, https://github.com/numaaron/numaaron/issues
Project-URL: Documentation, https://numaaron.org/doc/0.0
Project-URL: Source Code, https://github.com/numaaron/numaaron
Platform: Windows
Platform: Linux
Platform: Solaris
Platform: Mac OS-X
Platform: Unix
Classifier: Development Status :: 5 - Production/Stable
Classifier: Intended Audience :: Science/Research
Classifier: Intended Audience :: Developers
Classifier: License :: OSI Approved :: BSD License
Classifier: Programming Language :: C
Classifier: Programming Language :: Python
Classifier: Programming Language :: Python :: 3
Classifier: Programming Language :: Python :: 3.9
Classifier: Programming Language :: Python :: 3.10
Classifier: Programming Language :: Python :: 3.11
Classifier: Programming Language :: Python :: 3 :: Only
Classifier: Programming Language :: Python :: Implementation :: CPython
Classifier: Topic :: Software Development
Classifier: Topic :: Scientific/Engineering
Classifier: Typing :: Typed
Classifier: Operating System :: Microsoft :: Windows
Classifier: Operating System :: POSIX
Classifier: Operating System :: Unix
Classifier: Operating System :: MacOS
Requires-Python: >=3.9
License-File: LICENSE.txt
License-File: LICENSES_bundled.txt
